Workbook

Sheet Summary
A1: BOTIn POC — where we are
A2: Formulas over the Steps tab. Change a Status there and everything here updates. Statuses in use: Done · In progress · Not started · Blocked (waiting on somebody) · Parked (deliberately deferred — the Parked tab says what unparks each) · Out of scope (removed from the POC by decision — not waiting on anybody).
A3: TARGET: a working chatbot POC — L1 → L2 → resolution, API-driven, every tier and outcome type.
A5: Track | B5: Total | C5: Done | D5: Delivered | E5: In progress | F5: Blocked | G5: Parked | H5: Not started | I5: Out of scope | J5: Where it stands
A6: R&D ladder | B6: =COUNTIF(Steps!$B$2:$B$99,$A6) | C6: =COUNTIFS(Steps!$B$2:$B$99,$A6,Steps!$G$2:$G$99,"Done") | D6: =COUNTIFS(Steps!$B$2:$B$99,$A6,Steps!$G$2:$G$99,"Delivered") | E6: =COUNTIFS(Steps!$B$2:$B$99,$A6,Steps!$G$2:$G$99,"In progress") | F6: =COUNTIFS(Steps!$B$2:$B$99,$A6,Steps!$G$2:$G$99,"Blocked") | G6: =COUNTIFS(Steps!$B$2:$B$99,$A6,Steps!$G$2:$G$99,"Parked") | H6: =COUNTIFS(Steps!$B$2:$B$99,$A6,Steps!$G$2:$G$99,"Not started") | I6: =COUNTIFS(Steps!$B$2:$B$99,$A6,Steps!$G$2:$G$99,"Out of scope") | J6: COMPLETE. Six spikes, all green. Both go/no-go gates passed.
A7: Build | B7: =COUNTIF(Steps!$B$2:$B$99,$A7) | C7: =COUNTIFS(Steps!$B$2:$B$99,$A7,Steps!$G$2:$G$99,"Done") | D7: =COUNTIFS(Steps!$B$2:$B$99,$A7,Steps!$G$2:$G$99,"Delivered") | E7: =COUNTIFS(Steps!$B$2:$B$99,$A7,Steps!$G$2:$G$99,"In progress") | F7: =COUNTIFS(Steps!$B$2:$B$99,$A7,Steps!$G$2:$G$99,"Blocked") | G7: =COUNTIFS(Steps!$B$2:$B$99,$A7,Steps!$G$2:$G$99,"Parked") | H7: =COUNTIFS(Steps!$B$2:$B$99,$A7,Steps!$G$2:$G$99,"Not started") | I7: =COUNTIFS(Steps!$B$2:$B$99,$A7,Steps!$G$2:$G$99,"Out of scope") | J7: Phases 1-5 and 9-13 done. THE POC IS COMPLETE: 199+ tests green and the demo script runs 27/27 against a live service. docs/POC-ASSESSMENT.md carries the five answers and the verdict (GO, with two conditions). Remaining Build steps: the reconciliation job (61) and reading demo numbers (81). Phase 6/7 Transport and Phase 8 Violations are PARKED — see the Parked tab.
A8: LLM track | B8: =COUNTIF(Steps!$B$2:$B$99,$A8) | C8: =COUNTIFS(Steps!$B$2:$B$99,$A8,Steps!$G$2:$G$99,"Done") | D8: =COUNTIFS(Steps!$B$2:$B$99,$A8,Steps!$G$2:$G$99,"Delivered") | E8: =COUNTIFS(Steps!$B$2:$B$99,$A8,Steps!$G$2:$G$99,"In progress") | F8: =COUNTIFS(Steps!$B$2:$B$99,$A8,Steps!$G$2:$G$99,"Blocked") | G8: =COUNTIFS(Steps!$B$2:$B$99,$A8,Steps!$G$2:$G$99,"Parked") | H8: =COUNTIFS(Steps!$B$2:$B$99,$A8,Steps!$G$2:$G$99,"Not started") | I8: =COUNTIFS(Steps!$B$2:$B$99,$A8,Steps!$G$2:$G$99,"Out of scope") | J8: Blocked on procurement and real ticket text. Steps 7-9 need nobody and can start any time.
A9: TOTAL | B9: =SUM(B6:B8) | C9: =SUM(C6:C8) | D9: =SUM(D6:D8) | E9: =SUM(E6:E8) | F9: =SUM(F6:F8) | G9: =SUM(G6:G8) | H9: =SUM(H6:H8) | I9: =SUM(I6:I8)
A11: Complete | B11: =IFERROR(C9/B9,0) | C11: Done + Delivered | D11: =IFERROR((C9+D9)/B9,0)
A12: Complete (in scope) | B12: =IFERROR(C9/(B9-I9),0) | C12: Out-of-scope steps excluded from the denominator

Sheet Next up
A1: Step | B1: What | C1: Who | D1: Note
A2: — | B2: RUN tools/uat-probe-2.sql and uat-probe-3.sql | C2: You | D2: Closes four open items in one pass: the two wrong column names, paise-vs-rupees on transport_charges, N3 (the PayU link) and N2 (the order_status_code values). Command is in docs/WALKTHROUGH-NOTES.md §8.
A3: — | B3: FIX the two wrong column names once probe 2 lands | C3: Me | D3: arrived_at300_m and order_type do not exist. MySQL 1054 kills the WHOLE Transport SELECT, so on real data Transport does not degrade - it stops. Flip both requiredColumns markers from inferred to confirmed in the same edit.
A4: 55 | B4: BUILD the transport credit service | C4: Me | D4: ActionRegistry holds only AUTO_CREDIT_WALLET, so every transport T2 decides correctly then escalates. This is the difference between a demo where the bot explains what it would do and one where it moves money.
A5: — | B5: WIRE the job lat/long behind cs_address (Q6) | C5: Me | D5: Path 3 distance is null, so transport rules 8 and 9 are dead.
A6: — | B6: N4 — the SELECT-only GRANT on all three catalogs | C6: You | D6: IN PROGRESS, creds requested 15 Sept. 15 of 26 rules cannot read their facts without it. Confirm all three catalogs are on ONE MySQL host.
A7: — | B7: N2 — which unassign_status_code value is NR, and which is CR | C7: You | D7: BLOCKS transport rules 5a/5b, 6, 7. NR auto-credits and CR denies, so a wrong mapping pays the wrong partners.
A8: — | B8: N3 — which column links a wallet credit to a PayU transaction | C8: You | D8: BLOCKS alreadyCredited on Recharge. A wrong "not yet credited" pays twice.
A9: — | B9: DECISION: UPHOLD in the demo, or ship 4 of 5 outcome types? | C9: You | D9: Violations are out of scope, and UPHOLD went with them. VIOL_T1_SAMEDAY_LEAVE (SP_102, exists, needs no blocked answer) restores it for one concern. See docs/SCOPE-VIOLATIONS-OUT.md.
A10: — | B10: Partial-kilometre rounding — prorate, round up, or round down? | C10: You | D10: The Decision Matrix marks it OPEN. The code prorates, because that is the only one of the three that invents nothing.
A11: — | B11: D-1 — hosting | C11: You | D11: The Decision Brief lists it open; the Engineering Design states it settled. They disagree.
A12: — | B12: Job lat/long behind cs_address (Q6) — wire it | C12: Me | D12: Answered by the Decision Matrix: the job location is the CUSTOMER address, not tbl_order. Needed for Transport Path 3.
... A14: 10-11, 15-22 | B14: LLM measurement track | C14: Procurement | D14: Needs an API key and 150-200 labelled real Hinglish messages. Steps 7-9 and 12-14 are done and need nobody.

Sheet Parked
A1: What | B1: Steps | C1: Why it is parked | D1: What unparks it | E1: Who | F1: What the POC loses meanwhile
A2: Violations — OUT OF POC SCOPE (not parked) | B2: 62-67 | C2: Removed from the POC on 15 Sept. R1-R13 are sub-reasons under SP_103, but which column holds the sub-reason could not be established, and a query for a column that does not exist returns zero rows - which matched the REMOVE row and would have auto-removed violations never checked. V4 already had both concerns inactive, so nothing in the running service changes. | D2: Nothing. This is not waiting on anybody. A later violations phase would start from the reasoning in docs/DEFERRED.md D-A. | E2: — | F2: No volume: violations carry no June figure, so 9,542 and 7.7% are unchanged. What is lost is outcome-type coverage - UPHOLD, state-change-without-money and the concern-level durable counter, 3 of the 20 coverage-matrix rows. VIOL_T1_SAMEDAY_LEAVE (SP_102, exists, needs no blocked answer) would restore all three.
A3: Phase 6 — Transport end to end | B3: 53-57 | C3: To be done last, by agreement. The rate and the path selector are SETTLED - the Decision Matrix closed D-B and D-C. What is left is N2, the job lat/long behind cs_address, and a mock credit service. | D3: Answer N2 (which unassign_status_code is NR, which is CR). Then: cs_address wiring and the mock TransportCreditService at step 55. | E3: Project owner (D-B, D-C), then me | F3: The highest-volume concern in the build (5,615/month) decides correctly but cannot pay. In the demo it reaches a person instead — which is the true state, not a bug. Cap escalation IS demonstrable, because it produces a ticket rather than a payment.
A4: Phase 7 — the reconciliation job | B4: 61 | C4: BUILT 14 Sept. ReconciliationService reads both directions and corrects nothing; 5 tests green. Row kept for history. | D4: Done - nothing outstanding. | E4: Me | F4: The one check that would catch a payment the system believes it made and did not.
A5: The LLM track | B5: 10-11, 15-22 | C5: No API key and no model decision, so nothing can be measured. Blocked on procurement, not on design. | D5: A key and a budget owner. Steps 7-9 (task spec, NFRs, PII position) need nobody and can be written at any time. | E5: Procurement / project owner | F5: U-2, classifier accuracy, must be reported as NOT ASSESSED and never as passed. Fixtures written by the person building the classifier will always classify well; that is not evidence. The stub is a real bean, so routing, the confidence floor, the clarification loop and the degradation path are all built and demonstrable now.
A6: Agent-connect triggers B, D, E | B6: — | C6: Out of POC scope by the plan. Trigger A, the bounding rule and C's confidence threshold are in scope and built. | D6: Production work. Trigger D in particular needs the shared trigger table from the Engineering Design — it cannot be a column bolted onto each concern's own table without leaving silent holes in the ones that get missed. | E6: Production phase | F6: Nothing the POC was meant to answer. Stated here because it is easy to assume present.

Sheet Steps
A1: Step | B1: Track | C1: Phase | D1: Task | E1: Detail | F1: Type | G1: Status | H1: Note / blocked by | I1: Owner | J1: My notes
A2: 1 | B2: R&D ladder | C2: Component R&D ladder | D2: Run the Flowable process-engine spike | E2: Start here — it is the single dependency that could invalidate the architecture, and the one with the steepest learning curve. | F2: Task | G2: Done
A3: 2 | B3: R&D ladder | C3: Component R&D ladder | D3: Run the DMN spike, including the deliberately-wrong row order | F3: Task | G3: Done
A4: 3 | B4: R&D ladder | C4: Component R&D ladder | D4: Run the REQUIRES_NEW spike, both with and without the annotation | E4: The negative case matters more than the positive one — it proves the test would catch a regression. | F4: Task | G4: Done
A5: 4 | B5: R&D ladder | C5: Component R&D ladder | D5: Run the Togglz, Resilience4j and Flyway spikes | F5: Task | G5: Done
A6: 5 | B6: R&D ladder | C6: Component R&D ladder | D6: Run the FastAPI + Pydantic spike against a stubbed model response | F6: Task | G6: Done
A7: 6 | B7: R&D ladder | C7: Component R&D ladder | D7: GateWrite one page per component: what it does, how it is wired, and what surprised you | E7: If a component cannot be explained in a page, it is not understood well enough to build on. This page is also the seed of the production runbook. | F7: Gate | G7: Done
A8: 7 | B8: LLM track | C8: 3a — Define what the model has to do | D8: Write the task spec: closed-set classification of short Hinglish text, two variants — one concern's reason list, and the full L1/L2 taxonomy | E8: This is a narrow, cheap task. Naming it precisely stops the conversation drifting toward general-purpose assistants, which is a different and far more expensive purchase. | F8: Task | G8: Done | H8: Done — docs/LLM-TASK-SPEC.md §1. Closed-set classification into a taxonomy the service already owns. States what it is NOT, because each has been mistaken for it: not open-ended understanding, not a decision, not a threshold (the floor lives in the tables so a business owner can tune it), not a conversation. Every sentence a partner reads comes from a template — that is why a wrong classification costs a reroute, not a wrong promise about money.
A9: 8 | B9: LLM track | C9: 3a — Define what the model has to do | D9: Write the non-functional requirements | E9: Structured output support · p95 latency inside the 3s timeout with headroom · cost per thousand classifications at projected volume · rate limits and burst behaviour · data residency · retention and whether a zero-retention mode exists · availability commitment · how hard it is to swap out later. | F9: Task | G9: Done | H9: Done — §2. p95 under 3s because the client already enforces that timeout; a slower model degrades to a human, so you pay for capability you do not use. Cost stated per 1,000 CALLS, not per token: tokenisers differ and Hinglish tokenises worse than English. Degradation must stay indistinguishable from a no-match — already built.
A10: 9 | B10: LLM track | C10: 3a — Define what the model has to do | D10: Decide the PII position before talking to any vendor | E10: Partner free text can contain names, phone numbers and addresses. Decide whether text is redacted before it leaves the network, and whether that is a hard requirement or a preference — it eliminates some options outright. | F10: Task | G10: Done | H10: Done — §3. Recommended position: zero retention, no training on our data, processing region in the contract. SEQUENCE MATTERS: run the compliance filter BEFORE measuring accuracy, or the best-scoring candidate becomes the one everybody argues to accept. The Python service already enforces the boundary structurally — no DB credentials, no identifier field in the schema.
A11: 10 | B11: LLM track | C11: 3b — Build the harness | D11: Extract real free-text from historical tickets — unavailable; write Hinglish fixtures instead | E11: 20–30 strings, phrasing taken from the concern names themselves. Enough to exercise routing, the threshold, the clarification loop and degradation. Not enough to claim accuracy: fixtures written by the builder always classify well. Keep the real extract as a follow-up — the harness is built to accept it unchanged. | F11: Task | G11: Blocked | H11: No historical text — Hinglish fixtures instead
A12: 11 | B12: LLM track | C12: 3b — Build the harness | D12: Label the fixtures into the mapping's own categories anyway | E12: Categories come from the concern mapping, never invented. Labelling fixtures is still worth doing — it forces the category list to be exercised and surfaces overlaps between categories before a real test set exists. | F12: Task | G12: Blocked | H12: Depends on fixtures
A13: 12 | B13: LLM track | C13: 3b — Build the harness | D13: Write the scorer: accuracy, per-class confusion matrix, p95 latency, cost per call | E13: The confusion matrix matters more than the headline number — two categories bleeding into each other is fixable by merging them; uniform error is not. | F13: Task | G13: Done | H13: Done — classifier-service/harness/score.py. Reports accuracy, per-class confusion, false-match vs missed-match SEPARATELY (a false match sends the partner confidently into the wrong flow; a missed match hands them to a person, which is the design working), risk recall never averaged into accuracy, p95 against the 3s budget, and cost per 1,000 calls. A call failure scores as a no-match because that is what the service does with one.
A14: 13 | B14: LLM track | C14: 3b — Build the harness | D14: Define one prompt, versioned as a file, used identically across every candidate | E14: Tuning the prompt per vendor makes the comparison meaningless. | F14: Task | G14: Done | H14: Done — classifier-service/prompts/classify-v1.txt. Versioned so every candidate is measured on an IDENTICAL prompt: tuned per vendor, a model comparison becomes a prompt-engineering comparison and the winner is whoever was tuned last. {CATEGORIES} is substituted at call time from the ACTIVE catalogue, so a model can never name a concern nobody built.
A15: 14 | B15: LLM track | C15: 3c — Shortlist and decide | D15: Shortlist across three categories, not three brands | E15: Hosted frontier APIs — best accuracy, highest per-call cost, data leaves the network. Hosted small/cheap tiers — most vendors offer a smaller model that is usually sufficient for closed-set classification. Open-weight self-hosted — no per-call cost, no data egress, but infrastructure and ops become yours. Pricing and model lineups change constantly; pull current figures at decision time rather than trusting any written comparison. | F15: Task | G15: Done | H15: Done — §4. Three CATEGORIES, not three brands: hosted frontier, hosted cheap, self-hosted open. Evaluate the cheap tier FIRST — this is closed-set classification into under forty categories, not open-ended reasoning, and a frontier model would be paying for unused capability on every call forever. Exit criteria agreed before the numbers exist: >=90% holds, 75-90% raises the floor, <75% makes free text a fallback.
A16: 15 | B16: LLM track | C16: 3c — Shortlist and decide | D16: Run every candidate through the harness on the same test set and the same prompt | F16: Task | G16: Blocked | H16: Needs harness + a vendor
A17: 16 | B17: LLM track | C17: 3c — Shortlist and decide | D17: Check the cheap tier first | E17: This task is short-text classification into a fixed list. If a small model reaches the threshold, the frontier model's advantage is worth nothing here and costs several times more per call at 50,000 sessions a month. | F17: Task | G17: Blocked | H17: Needs step 15
A18: 17 | B18: LLM track | C18: 3c — Shortlist and decide | D18: DecisionRecord the choice with its numbers, and the runner-up with its numbers | E18: The runner-up matters: it is the fallback if the first choice fails a security review, changes pricing, or degrades. | F18: Decision | G18: Blocked | H18: Needs step 15
A19: 18 | B19: LLM track | C19: 3d — Procure and secure the key | D19: Identify the budget owner and get a spend ceiling approved against the measured cost-per-call | E19: Bring a number from step 15, not an estimate. | F19: Task | G19: Blocked | H19: Needs measured cost from step 15
A20: 19 | B20: LLM track | C20: 3d — Procure and secure the key | D20: Security review and data-processing agreement | E20: Usually the longest single item. Start it the moment the shortlist exists — it can run against two candidates in parallel. | F20: Task | G20: Blocked | H20: Needs shortlist
A21: 20 | B21: LLM track | C21: 3d — Procure and secure the key | D21: Billing account, then separate keys per environment | F21: Task | G21: Blocked | H21: Needs step 19
A22: 21 | B22: LLM track | C22: 3d — Procure and secure the key | D22: Keys into a secret manager with a rotation policy — never in the repo, never in a plain environment file | E22: Decide rotation cadence and who holds the break-glass copy at the same time, not later. | F22: Task | G22: Blocked | H22: Needs step 20
A23: 22 | B23: LLM track | C23: 3d — Procure and secure the key | D23: Spend alerting on the billing account | E23: A retry loop against a paid API is a financial incident, not just a bug. | F23: Task | G23: Blocked | H23: Needs step 20
A24: 23 | B24: Build | C24: Phase 1 — Skeleton and data model | D24: Spring Boot service, standalone, structured as the production package layout | E24: Split by layer from day one: api, session, catalogue, process, decision, facts, action, safety, agent. Renaming packages later is cheap; discovering the boundaries later is not. | F24: Task | G24: Done | H24: Done — verified by mvn test on 14 Sep, 6/6 green
A25: 24 | B25: Build | C25: Phase 1 — Skeleton and data model | D25: Dependencies: web, data-jpa, flyway, flowable-spring-boot-starter, togglz, resilience4j, driver, test containers | F25: Task | G25: Done | H25: Done — all versions resolve; Flyway module corrected to Boot 3.2 line
A26: 25 | B26: Build | C26: Phase 1 — Skeleton and data model | D26: Two datasources: the service's own schema, and a second, read-only one | E26: Points at a seeded local database for now, at the replica later — the code does not know the difference. Keep it read-only at the connection level from day one, so the substitution never quietly becomes a write path. | F26: Task | G26: Done | H26: Done — UAT is the SECOND datasource, read-only, no JPA/Flyway/Flowable on it
A27: 26 | B27: Build | C27: Phase 1 — Skeleton and data model | D27: Flyway migrations for six tables: concern_catalogue, help_session, ticket, ticket_action, conversation_message, escalation_context | F27: Task | G27: Done | H27: Done — V1__core_schema.sql applies cleanly
A28: 27 | B28: Build | C28: Phase 1 — Skeleton and data model | D28: Plus one the mapping forces: sp_counter — durable per-SP tallies with a reset boundary | E28: The pooled emergency count, the monthly period-leave count and the 25-job cycle allowances are state this engine owns, not facts it reads. Nothing in the earlier design held them. | F28: Task | G28: Done | H28: Done — sp_counter included
A29: 28 | B29: Build | C29: Phase 1 — Skeleton and data model | D29: Unique constraint on ticket_action.idempotency_key; index ticket(sp_id, l2_concern, created_at) | F29: Task | G29: Done | H29: Done — asserted by SchemaAndCatalogueTest
A30: 29 | B30: Build | C30: Phase 1 — Skeleton and data model | D30: Entities, repositories, and HelpSessionService / TicketService / TicketActionRecorder | F30: Task | G30: Done | H30: Done — entities + repositories + recorder
A31: 30 | B31: Build | C31: Phase 1 — Skeleton and data model | D31: CriticalrecordAttempt() annotated @Transactional(propagation = REQUIRES_NEW), with the paired test from spike 3 promoted into the real test suite | F31: Critical | G31: Done | H31: Done — rollback test green in the real suite
A32: 31 | B32: Build | C32: Phase 1 — Skeleton and data model | D32: CheckpointApp boots on an empty database; our seven tables and ~25 ACT_* tables all appear | F32: Checkpoint | G32: Done | H32: Done — 6/6 tests pass; 7 tables + ACT_* confirmed on H2. Postgres boot still to run.
A33: 32 | B33: Build | C33: Phase 2 — Catalogue and L1 → L2 routing | D33: Seed concern_catalogue from the generated CSV — all 38 rows, 30 of them inactive | E33: Seed the full taxonomy even though only 8 are built. It makes the L1 menu real, and an SP selecting an unbuilt concern must degrade gracefully rather than 500. | F33: Task | G33: Done | H33: Done — all 38 seeded, 8 active (V2)
A34: 33 | B34: Build | C34: Phase 2 — Catalogue and L1 → L2 routing | D34: Add the columns this mapping needs beyond the original design: mandatory_human, outcome_types, active | F34: Task | G34: Done | H34: Done — V3 adds outcome_types, backfilled for all 38; mandatory_human + active already in V1
A35: 34 | B35: Build | C35: Phase 2 — Catalogue and L1 → L2 routing | D35: GET /help/concerns returns L1 paths; GET /help/concerns/{l1} returns active L2s | E35: Driven entirely from the catalogue. No hard-coded list anywhere. | F35: Task | G35: Done | H35: Done — GET /help/concerns and /help/concerns/{l1}, derived from the table, no hard-coded list
A36: 35 | B36: Build | C36: Phase 2 — Catalogue and L1 → L2 routing | D36: POST /help/sessions and POST /help/sessions/{id}/input with a nextStep descriptor | E36: Types: menu, dropdown, text, message, deeplink, closed. The backend owns all flow logic; the client is a renderer. | F36: Task | G36: Done | H36: Done — POST /help/sessions + /input, nextStep descriptor persisted as JSON on help_session
A37: 36 | B37: Build | C37: Phase 2 — Catalogue and L1 → L2 routing | D37: GET /help/sessions/{id} for reconnect | E37: Reads nextStep from the session row, never from process variables — those are deleted when an instance completes. | F37: Task | G37: Done | H37: Done — GET /help/sessions/{id}; reconnect payload asserted identical to the response payload
A38: 37 | B38: Build | C38: Phase 2 — Catalogue and L1 → L2 routing | D38: Selecting an inactive concern returns a defined "not available" step | E38: 30 of 38 rows are inactive. This path will be hit constantly. | F38: Task | G38: Done | H38: Done — CONCERN_NOT_AVAILABLE for inactive, unknown, and wrong-path codes; status CLOSED_NOT_AVAILABLE
A39: 38 | B39: Build | C39: Phase 3 — First concern end to end — T0 | D39: FORGET_MPIN: BPMN with a start event, one Service Task, one end event | F39: Task | G39: Done | H39: Done — forget-mpin.bpmn20.xml: start, one Service Task, end
A40: 39 | B40: Build | C40: Phase 3 — First concern end to end — T0 | D40: Returns a deeplink step and closes the session | F40: Task | G40: Done | H40: Done — deeplink step (configurable), session closes CLOSED_DEFLECTED
A41: 40 | B41: Build | C41: Phase 3 — First concern end to end — T0 | D41: CheckpointAssert zero rows in ticket after the session closes | E41: This is Gate 1 made testable. T0 creating a ticket is the most likely silent bug in the whole design, because everything downstream assumes a ticket exists. | F41: Checkpoint | G41: Done | H41: Done — CHECKPOINT PASSED. Zero tickets by count, by SP, and by session. 27/27 green.
A42: 41 | B42: Build | C42: Phase 4 — Fact providers and shared services | D42: ConcernFactProvider interface and the generic fetchFactsDelegate that resolves a bean by catalogue row | F42: Task | G42: Done | H42: Done — ConcernFactProvider + FactProviderRegistry, fails at startup on a missing/duplicate provider
A43: 42 | B43: Build | C43: Phase 4 — Fact providers and shared services | D43: Shared service: haversine + hub radius, distance measured from the radius edge | E43: Used by Transport path 3 now, R1 later. Build it as a service with its own tests, not a private method. | F43: Task | G43: Done | H43: Done — GeoService. Formula copied from empapi; measured from the RADIUS EDGE; radius = MAX(end) of hub slabs
A44: 43 | B44: Build | C44: Phase 4 — Fact providers and shared services | D44: Shared service: Express/Standard delivery TAT with the 11 PM deadline | E44: Used by PROD_DELIVERY_DELAY and VIOL_R9. The mapping explicitly flags that R9 previously used a flat 3 days — the drift already happened once. | F44: Task | G44: Done | H44: Done — DeliveryTatService. Shared by PROD_DELIVERY_DELAY and VIOL_R9. Express by PINCODE. Zone stated.
A45: 44 | B45: Build | C45: Phase 4 — Fact providers and shared services | D45: Shared service: duplicate-credit guard, keyed per action type | E45: Order ID for transport, PayU txn id for recharge. One service, two key strategies. | F45: Task | G45: Done | H45: Done — DuplicateCreditGuard. NET position, not EXISTS(CREDIT) — DEBIT/TRANSPORT is real
A46: 45 | B46: Build | C46: Phase 4 — Fact providers and shared services | D46: Shared service: counter service over sp_counter, with explicit reset boundaries | E46: Calendar month for period leave, rolling 25-job cycle for allowances. The boundary definition is part of the contract. | F46: Task | G46: Done | H46: Done — SpCounterService. period_key is part of the PK, so reset is free. REQUIRES_NEW.
A47: 46 | B47: Build | C47: Phase 4 — Fact providers and shared services | D47: Write the eight fact providers against the seeded schema, one signal at a time | E47: Real SQL, real column names. Ask for a schema-only dump to shape it — DDL with no rows is a much smaller ask than access and carries no data risk. Where even the schema is guessed, say so in the register. | F47: Task | G47: Done | H47: Done — 6 providers (2 concerns parked, see DEFERRED D-A). Every UAT column declared as confirmed/inferred; UatSchemaProbe checks them at startup. ProviderContractTest runs with UAT OFF and asserts fact names match the tables. 111/111 green.
A48: 47 | B48: Build | C48: Phase 4 — Fact providers and shared services | D48: Key outputMaintain a live signal-availability register as you go | E48: Per signal: verified / assumed / not available / exists elsewhere — and where the schema itself was guessed, say so. This register is the answer to whether Layer 6 is an integration or a build, and it is the POC's most reusable artifact. A signal that cannot be read becomes a mock with a recorded reason — never a quietly invented value. | F48: Key output | G48: Done | H48: Done — docs/SIGNAL-REGISTER.md + SignalRegisterTest. 113/113 green. FINDING: 11 of the 26 rules on active concerns cannot fire today because a signal they read is never populated. With UAT off only FORGET_MPIN resolves (738 of 9,542/month, 7.7%). GATE: TRANSPORT_AUTO_CREDIT must stay off while computedAmountPaise is absent — the Rs300 cap cannot fire.
A49: 48 | B49: Build | C49: Phase 5 — Decision tables | D49: Author one .dmn per concern, hit policy FIRST, from the generated rule rows | F49: Task | G49: Done | H49: Done — 8 .dmn files, hitPolicy FIRST, 32 rows (26 mapping + 5 catch-alls + 1 added)
A50: 49 | B50: Build | C50: Phase 5 — Decision tables | D50: Implement the derived Transport path selector as a single named fact | E50: transportPath, computed by TransportFactProvider, fed to the table as an input column. Charge-not-credited → Path 1; cancelled → Path 2; outside hub radius → Path 3; otherwise no entitlement. Mark it as an assumption in code and in the register. When the real rule arrives it is one method and one column. | F50: Task | G50: Done | H50: Done — TransportPathSelector, own class + own test. STILL AN ASSUMPTION
A51: 50 | B51: Build | C51: Phase 5 — Decision tables | D51: Add a terminal catch-all row to every table | E51: Thirteen concerns in the mapping have no default branch. Under FIRST, a case matching no row returns nothing and the gateway has nowhere to go. | F51: Task | G51: Done | H51: Done — catch-all last in every table; DecisionService throws on a null result
A52: 51 | B52: Build | C52: Phase 5 — Decision tables | D52: Move every threshold into the table: Rs300, Rs50/km, 11 PM, the cycle allowances | E52: No numeric constant from the caps register belongs in Java. | F52: Task | G52: Done | H52: Done — Rs300, Rs50/km, 1 period leave/month, 1 product allowance/cycle, 0.7 floor all in-table
A53: 52 | B53: Build | C53: Phase 5 — Decision tables | D53: CheckpointA test per rule, feeding fact maps straight to DmnDecisionService — 26 rules, 26 assertions, plus one per catch-all | F53: Checkpoint | G53: Done | H53: Done — CHECKPOINT PASSED. 70/70 green. Found 2 row-order defects in money rules.
A54: 53 | B54: Build | C54: Phase 6 — The anchor concern — Transport | D54: BPMN: start → fetch facts → business rule → gateway on tier → gateway on flag → action → finalize | F54: Task | G54: Parked | H54: PARKED - to be done last, by agreement. D-B (Rs50/km from the radius EDGE) and D-C (the path selector) are now CLOSED by the Decision Matrix. What remains: N2 - which unassign_status_code is NR vs CR (NR auto-credits, CR denies) - plus wiring the job lat/long behind cs_address, and the mock credit service at step 55.
A55: 54 | B55: Build | C55: Phase 6 — The anchor concern — Transport | D55: Order-ID capture step before facts are fetched | F55: Task | G55: Parked | H55: PARKED - to be done last, by agreement. D-B (Rs50/km from the radius EDGE) and D-C (the path selector) are now CLOSED by the Decision Matrix. What remains: N2 - which unassign_status_code is NR vs CR (NR auto-credits, CR denies) - plus wiring the job lat/long behind cs_address, and the mock credit service at step 55.
A56: 55 | B56: Build | C56: Phase 6 — The anchor concern — Transport | D56: Mock TransportCreditService — writes to a mock ledger table, never to a real system | F56: Task | G56: Parked | H56: PARKED - to be done last, by agreement. D-B (Rs50/km from the radius EDGE) and D-C (the path selector) are now CLOSED by the Decision Matrix. What remains: N2 - which unassign_status_code is NR vs CR (NR auto-credits, CR denies) - plus wiring the job lat/long behind cs_address, and the mock credit service at step 55.
A57: 56 | B57: Build | C57: Phase 6 — The anchor concern — Transport | D57: Response templates keyed by DMN action, one per outcome | E57: Nine rules produce six distinct messages. Templates are files, not string literals, and no model writes any of them. | F57: Task | G57: Parked | H57: PARKED - to be done last, by agreement. D-B (Rs50/km from the radius EDGE) and D-C (the path selector) are now CLOSED by the Decision Matrix. What remains: N2 - which unassign_status_code is NR vs CR (NR auto-credits, CR denies) - plus wiring the job lat/long behind cs_address, and the mock credit service at step 55.
A58: 57 | B58: Build | C58: Phase 6 — The anchor concern — Transport | D58: Major checkpointAll nine transport rules driven end to end by API call, each landing on its expected outcome | F58: Major checkpoint | G58: Parked | H58: PARKED - to be done last, by agreement. D-B (Rs50/km from the radius EDGE) and D-C (the path selector) are now CLOSED by the Decision Matrix. What remains: N2 - which unassign_status_code is NR vs CR (NR auto-credits, CR denies) - plus wiring the job lat/long behind cs_address, and the mock credit service at step 55.
A59: 58 | B59: Build | C59: Phase 7 — Money safety | D59: TestRollback: record attempt → simulate a successful external call → throw from a later delegate → assert the Flowable transaction rolled back and the ticket_action row survived | F59: Test | G59: Done | H59: Done — TicketActionRecorderTest: 'the ATTEMPTED row survives a rollback of the calling transaction', plus the negative test from spike 3 (remove REQUIRES_NEW and the row vanishes), so the test has teeth. Proven for the RECHARGE path in Phase 12a; the mechanism is concern-independent.
A60: 59 | B60: Build | C60: Phase 7 — Money safety | D60: TestIdempotency: fire the identical credit twice → one ledger entry, second short-circuits on the unique key | F60: Test | G60: Done | H60: Done — MockPayUGateway + MoneyPathTest: the same order raised in a NEW session pays once. Two tickets (correctly — two contacts), one attempt row, one payment. Keyed on the gateway's order id, not our ticket id, which is what makes it collide across sessions and restarts.
A61: 60 | B61: Build | C61: Phase 7 — Money safety | D61: TestCap: a case computing above Rs300 produces a ticket and moves no money at all | E61: The failure mode to rule out is a clamped Rs300 payment. The rule says escalate, not cap-and-pay. | F61: Test | G61: Done | H61: Done — the cap escalates rather than clamping. DmnHotRedeployTest proves the rule fires (T3 / TICKET_EXCEEDS_CAP / TICKET); DemoFixturesTest drives it from a fixture order at Rs450. Clamping to Rs300 would be a silent underpayment nobody ever sees.
A62: 61 | B62: Build | C62: Phase 7 — Money safety | D62: Reconciliation job: sum ticket_action credits against the mock ledger, alert on any mismatch | F62: Task | G62: Done | H62: Done — ReconciliationService. Reads BOTH directions, and they are not equally interesting: 'we say we paid, the gateway did not' is bad but visible (a partner complains). 'The gateway paid, we have no record' is worse and SILENT — nobody complains about money they received, and no amount of reading our own tables would ever show it. It reports and corrects nothing: a job that fixes what it finds is a second, unsupervised payment path running on exactly the cases nobody understood the first time. FOUND A REAL BUG: amount_paise existed on ticket_action since the first migration and NOTHING EVER WROTE IT — every row said a credit succeeded and none said how much. Invisible until something tried to sum them. 223/223 green.
A63: 62 | B63: Build | C63: Phase 8 — Violations — state change without money | D63: VIOL_R5_PERIODS: violation lookup, monthly counter, two outcomes | F63: Task | G63: Out of scope | H63: OUT OF POC SCOPE, 15 Sept. The R1-R13 sub-reason could not be located in the schema; building on a guess would have auto-removed unchecked violations. Not blocked - nobody needs to answer anything. Tables and tests kept. See docs/SCOPE-VIOLATIONS-OUT.md
A64: 63 | B64: Build | C64: Phase 8 — Violations — state change without money | D64: Mock ViolationService.remove() | E64: The bot removes a violation. It never removes a strike. The mock must model the backend recomputing the strike once no violations remain for that day — otherwise the POC teaches the wrong contract. | F64: Task | G64: Out of scope | H64: OUT OF POC SCOPE, 15 Sept. The R1-R13 sub-reason could not be located in the schema; building on a guess would have auto-removed unchecked violations. Not blocked - nobody needs to answer anything. Tables and tests kept. See docs/SCOPE-VIOLATIONS-OUT.md
A65: 64 | B65: Build | C65: Phase 8 — Violations — state change without money | D65: UPHOLD as a first-class outcome, with its own template class | E65: Not a T1 answer. It is the rejection of an appeal — the case most likely to produce a dissatisfied partner. | F65: Task | G65: Out of scope | H65: OUT OF POC SCOPE, 15 Sept. The R1-R13 sub-reason could not be located in the schema; building on a guess would have auto-removed unchecked violations. Not blocked - nobody needs to answer anything. Tables and tests kept. See docs/SCOPE-VIOLATIONS-OUT.md
A66: 65 | B66: Build | C66: Phase 8 — Violations — state change without money | D66: VIOL_R9_NO_PRODUCT, reusing the TAT service from step 43 | F66: Task | G66: Out of scope | H66: OUT OF POC SCOPE, 15 Sept. The R1-R13 sub-reason could not be located in the schema; building on a guess would have auto-removed unchecked violations. Not blocked - nobody needs to answer anything. Tables and tests kept. See docs/SCOPE-VIOLATIONS-OUT.md
A67: 66 | B67: Build | C67: Phase 8 — Violations — state change without money | D67: CheckpointChange the TAT rule once; assert both PROD_DELIVERY_DELAY and VIOL_R9 change together | E67: This is the shared-service claim, tested rather than asserted. | F67: Checkpoint | G67: Out of scope | H67: OUT OF POC SCOPE, 15 Sept. The R1-R13 sub-reason could not be located in the schema; building on a guess would have auto-removed unchecked violations. Not blocked - nobody needs to answer anything. Tables and tests kept. See docs/SCOPE-VIOLATIONS-OUT.md
A68: 67 | B68: Build | C68: Phase 8 — Violations — state change without money | D68: Counter test: second period leave in a month upholds; the counter resets at the boundary | F68: Task | G68: Out of scope | H68: OUT OF POC SCOPE, 15 Sept. The R1-R13 sub-reason could not be located in the schema; building on a guess would have auto-removed unchecked violations. Not blocked - nobody needs to answer anything. Tables and tests kept. See docs/SCOPE-VIOLATIONS-OUT.md
A69: 68 | B69: Build | C69: Phase 9 — Agent connect | D69: T3 branch ends on a User Task in a named queue | F69: Task | G69: Done | H69: Done — userTask agentConnect in concern-generic.bpmn20.xml, candidate group from a process variable. 128/128 green.
A70: 69 | B70: Build | C70: Phase 9 — Agent connect | D70: escalationContextDelegate writes the snapshot: concern, facts, which rule fired, prior actions | F70: Task | G70: Done | H70: Done — EscalationContextDelegate. Facts + tier + action + recent tickets + prior ATTEMPTED actions, written before the wait and never recomputed. New trigger_reason value CONCERN for a table-driven T3.
A71: 70 | B71: Build | C71: Phase 9 — Agent connect | D71: Agent API: GET /agent/tasks, POST /agent/tasks/{id}/claim, GET /tickets/{id}/escalation-context, GET /tickets/{id}/conversation, POST /agent/tasks/{id}/complete | E71: Chat handoff, not a call. The ticket waits in a queue; an agent picks it up. No telephony anywhere in the POC. | F71: Task | G71: Done | H71: Done — GET /agent/tasks, POST claim, POST complete, GET /tickets/{id}/escalation-context. The queue IS the Flowable task store. Not authenticated (D-7).
A72: 71 | B72: Build | C72: Phase 9 — Agent connect | D72: The restart testReach a User Task → kill the JVM → restart → claim and complete → the process resumes and finishes | E72: If this fails, stop. The entire reason for embedding a process engine collapses, and the design needs rethinking before anything else is built. | F72: The restart test | G72: Done | H72: Done — asserted in-process: task, variables and ticketId read back from ACT_RU_* holding nothing from the originating request. JVM-kill evidence is spike 1.
A73: 72 | B73: Build | C73: Phase 9 — Agent connect | D73: Agent completion writes back to the ticket and closes the session | F73: Task | G73: Done | H73: Done — completion wakes the process; the process closes the ticket and session. Agent note reaches the partner verbatim.
A74: 73 | B74: Build | C74: Phase 10 — CSAT and the bounding rule | D74: Add csat as a nextStep type, emitted after every T0, T1 and T2 resolution | E74: T0 creates no ticket, so its answer lands on the session row. The PRD says CSAT closes "the ticket" in every case — for T0 there is no ticket. Store it on whichever row exists and flag the wording. | F74: Task | G74: Done | H74: Done — csatExpected + agentOffered on SessionView, POST /help/sessions/{id}/csat. Session stays CLOSED while the question is outstanding.
A75: 74 | B75: Build | C75: Phase 10 — CSAT and the bounding rule | D75: DecisionChoose the mechanism and record why | E75: The process currently ends before CSAT is answered — finalizeDelegate completes the instance and its runtime row is deleted, so there is nothing left to resume. Either keep the instance alive on a Receive Task waiting for a CSAT event, or have CSAT = No start a second short process against the same ticket. Parked instances versus a split audit trail. This is O-15 in the Engineering Design, and the POC is where it gets settled because this codebase is the production seed. | F75: Decision | G75: Done | H75: Done — DECIDED, settles O-15: the instance completes and the answer arrives on its own endpoint. Holding it alive would charge runtime state to every T0/T1/T2 to serve the unhappy few, and would make the instance-completes property conditional.
A76: 75 | B76: Build | C76: Phase 10 — CSAT and the bounding rule | D76: Implement it, with a boundary timer for "never answered" | E76: Most partners will not answer. The no-answer path is the default case, not the exception — build it first and the happy path second. | F76: Task | G76: Done | H76: Done — NO TIMER NEEDED. Nothing is held open, so nothing can time out. "Never answered" = csat_result stays null, countable in a report. One timer, one job and one class of stuck session removed.
A77: 76 | B77: Build | C77: Phase 10 — CSAT and the bounding rule | D77: Trigger A — CSAT = No offers an agent, creating a T3 escalation against the same ticket | F77: Task | G77: Done | H77: Done — trigger A. Escalates the SAME ticket where one exists; opens one where the resolution was a T0.
A78: 77 | B78: Build | C78: Phase 10 — CSAT and the bounding rule | D78: The bounding rule — CSAT = Yes on a T0–T2 case suppresses the agent option entirely | E78: Enforced in ticket-closure logic, never by the client choosing not to render a button. A suppression rule the client can ignore is not a suppression rule. | F78: Task | G78: Done | H78: Done — the bounding rule, on SessionView.agentOffered, enforced in closure logic and never in the client.
A79: 78 | B79: Build | C79: Phase 10 — CSAT and the bounding rule | D79: Trigger B exception — a concern flagged mandatory_human offers an agent regardless of the CSAT answer | E79: Only the CSAT exception is in POC scope. B's full pre-flight gate — routing to an agent before any facts are fetched — is not built here. | F79: Task | G79: Done | H79: Done — trigger B exception: a mandatory_human concern keeps the agent option whatever the partner answered.
A80: 79 | B80: Build | C80: Phase 10 — CSAT and the bounding rule | D80: TestA satisfied T2 case returns no agent affordance at all in the response payload | E80: Assert on the payload, not the UI. If the field is present and merely false, a future client will render it. | F80: Test | G80: Done | H80: Done — a satisfied case returns agentOffered=false and creates no ticket.
A81: 80 | B81: Build | C81: Phase 10 — CSAT and the bounding rule | D81: TestA dissatisfied T2 case offers an agent, the task appears in the queue, and the context endpoint serves it | F81: Test | G81: Done | H81: Done — a dissatisfied case escalates, appears in the agent queue with triggerReason A, and the context endpoint carries the exact answer the partner rejected.
A82: 81 | B82: Build | C82: Phase 10 — CSAT and the bounding rule | D82: Record the CSAT response rate and the trigger-A rate from the demo run | E82: These two numbers are what the bounding rule protects. Without them the 10–20% agent-connect ceiling cannot be verified even in principle. | F82: Task | G82: Not started | H82: Gated on step 95 — there is no demo run to measure yet. The mechanism is built and tested; this step is reading numbers off it.
A83: 82 | B83: Build | C83: Phase 11 — Free text and reroute | D83: Python service: POST /classify and POST /classify-intent, Pydantic-validated, no database credentials | F83: Task | G83: Done | H83: Done — FastAPI + Pydantic, /classify and /classify-intent, closed enums, bounded confidence, no DB and no identifiers. No model wired in; classify_text is a placeholder and the contract around it is real.
A84: 83 | B84: Build | C84: Phase 11 — Free text and reroute | D84: Deterministic stub behind the real client interface, keyed on fixture strings | F84: Task | G84: Done | H84: Done — StubClassifierClient, a REAL bean chosen when CLASSIFIER_URL is unset. Deterministic keyword matching; NO_MATCH for everything else.
A85: 84 | B85: Build | C85: Phase 11 — Free text and reroute | D85: ClassifierClient with a 3s timeout and a circuit breaker; both failure modes set tier = T3 | F85: Task | G85: Done | H85: Done — HttpClassifierClient, 3s timeout + Resilience4j breaker. Both failure modes return the same value as an honest no-match, so there is no second code path under load.
A86: 85 | B86: Build | C86: Phase 11 — Free text and reroute | D86: Entry-point free text: POST /help/sessions with freeText and no L1/L2 → classify-intent → back-fill the session → start the matching process | E86: Downstream is identical to a menu selection. The escalation_context must carry the original text, the matched concern and the confidence, so a reader can see how the system got there. | F86: Task | G86: Done | H86: Done — entry free text routes into the TRIAGE concern, which does the routing. Not a second mechanism beside RerouteDelegate. One model call per turn: the classification is carried into the process.
A87: 86 | B87: Build | C87: Phase 11 — Free text and reroute | D87: In-concern free text: VIOL_R4_OTHERS → text names a different reason → reroute to that flow | E87: Reroute is a new mechanism. Decide and document whether it ends the process and starts another, or is a BPMN call activity — and what happens to the ticket id either way. | F87: Task | G87: Done | H87: Done — RerouteDelegate. Session MOVES rather than forking. Cannot reroute into a triage concern; target must be active and built. Caught a real bug: reroute was crossing Gate 1. AND A SECOND ONE, LATER: the IN-CONCERN path — the one this step actually describes — was unreachable through the API. handleL2 took the selection and discarded the text, so the concern ran with nothing to classify. Every test drove reroute from the ENTRY point instead. Built, green, documented as done, and dead. Found by tools/demo-run.sh on its third run; RerouteTest now has the test that would have caught it.
A88: 87 | B88: Build | C88: Phase 11 — Free text and reroute | D88: Clarification loop: clarificationAttempts variable, re-prompt, escalate on the third failure | E88: The PRD requires two clarification attempts before an agent. Escalating on the first low-confidence result inflates the agent-connect rate directly. | F88: Task | G88: Done | H88: Done — clarification loop on the session (V6 clarification_attempts), not in BPMN: at the entry point no process exists yet. Re-prompt twice, different wording each time, then a person with the whole transcript. Risk skips the loop.
A89: 88 | B89: Build | C89: Phase 11 — Free text and reroute | D89: CheckpointKill the Python service mid-session — the flow degrades to T3, no error reaches the caller | F89: Checkpoint | G89: Done | H89: Done — CHECKPOINT PASSED. A client throwing on every call degrades to a human with nothing reaching the partner. 152/152 green.
A90: 89 | B90: Build | C90: Phase 12 — External dependency and kill switch | D90: RECHARGE_DEBIT_NO_CREDIT against a mock PayU with switchable status and induced failures | F90: Task | G90: Done | H90: Done — MockPayUGateway (switchable status, amounts, failNextCalls(n)) + WalletCreditService + ActionRegistry. PerformActionDelegate is the only place money moves: record the attempt AND COMMIT IT, call, record the outcome, never retry. A failed action moves the TICKET to T3 too, not just the process variables — otherwise the failure counts as automation that worked. 165/165 green.
A91: 90 | B91: Build | C91: Phase 12 — External dependency and kill switch | D91: Idempotency keyed on the third-party transaction id, not our own | E91: A different key strategy from transport. Worth proving the guard handles both. | F91: Task | G91: Done | H91: Done — key is AUTO_CREDIT_WALLET:ref:<PayU order id>, not :ticket:<id>. A second conversation about the same failed recharge is correctly a second ticket, and must not be able to produce a second payment. Actions with no external reference keep the ticket-scoped key, so the shape degrades to the safe thing. A duplicate returns INFORM_ALREADY_CREDITED at T1 — the partner is told, not silently ignored.
A92: 91 | B92: Build | C92: Phase 12 — External dependency and kill switch | D92: BotinFeature enum, JDBCStateRepository, console mounted and authenticated | E92: Even in a POC. An unauthenticated console that flips money-moving behaviour is a habit that survives into production. | F92: Task | G92: Done | H92: Done — flags now live in the primary database (JDBCStateRepository, no cache: a cached kill switch has a TTL, and a kill switch with a delay is not a kill switch). The TOGGLZ table is Togglz's own, as ACT_* is Flowable's; Flyway owns our tables. Console mounted by TogglzConsoleConfig, NOT the starter: with no TOGGLZ_CONSOLE_PASSWORD the servlet is not registered at all, so a misconfiguration 404s the page instead of exposing it. Authenticated by a filter on that one path rather than spring-boot-starter-security, which would secure every endpoint and enable CSRF on every POST — a test asserts the partner API still answers with no credentials. D-7 replaces it with Spring Security before Wave 1. A flag with no row reads OFF, so a fresh database pays nobody; every switch's position is logged at startup because off and never-configured look identical.
A93: 92 | B93: Build | C93: Phase 12 — External dependency and kill switch | D93: CheckpointFlip the transport flag while running — next request routes to T3, no restart, and the partner still gets served | F93: Checkpoint | G93: Done | H93: Done — CHECKPOINT PASSED. KillSwitch gates the T2 in DecideDelegate, before any call is made. Flag off = do not automate, send to a human; the partner is still served and no error reaches them. A concern with no flag is allowed, so adding a concern cannot ship it accidentally disabled.
A94: 93 | B94: Build | C94: Phase 12 — External dependency and kill switch | D94: CheckpointEdit the Rs300 cap in the .dmn file, redeploy that file alone, behaviour changes with no Java rebuild | F94: Checkpoint | G94: Done | H94: Done — CHECKPOINT PASSED. Rs250 paid under the Rs300 cap; cap edited to Rs200 in transport-not-received-decision.dmn; that one file redeployed into the running engine; same claim, same facts, now TICKET_EXCEEDS_CAP to a person. No rebuild, no restart. A third test asserts 30000 appears in no Java source anywhere — a constant agreeing with the table today becomes a silent disagreement after tomorrow's redeploy. 181/181 green, first run.
A95: 94 | B95: Build | C95: Phase 13 — Demo surface and assessment | D95: OpenAPI spec published from the running service | F95: Task | G95: Done | H95: Done — springdoc publishes the spec FROM the running service, so it cannot drift from the code. OpenApiPublishedTest names all ten endpoints explicitly: a springdoc that stops scanning a controller does not throw, it publishes a smaller document, and that looks exactly like a correct one unless something counts. The description carries the flow-ownership split, which an integrator would otherwise assume the other way round.
A96: 95 | B96: Build | C96: Phase 13 — Demo surface and assessment | D96: A scripted run covering all seventeen cases in the coverage matrix, as a single executable file | E96: Curl or a REST client collection. The demo is the script — reproducible, not a live improvisation. | F96: Task | G96: Done | H96: Done and EXECUTED — 27/27 checks pass against a running service. tools/demo-run.sh covers 17 of the 20 coverage-matrix rows, asserts every case and exits non-zero on failure. Runs on in-memory H2 so it needs nothing installed. Three rounds of red before green, and the failures were worth more than the script: a doubled-output bug, a shell variable that never escaped its subshell, three guessed L1 codes, a wrong assumption about where CSAT lives on the contract, and one genuine unreachable feature (step 86).
A97: 96 | B97: Build | C97: Phase 13 — Demo surface and assessment | D97: A seed fixture set: SPs, bookings, violations, wallet states that exercise every rule | F97: Task | G97: Done | H97: Done — demo/fixtures.json + DemoFixtures, @Profile("demo"), FAILS AT STARTUP beside a real UAT datasource. Raw rows, not conclusions: path selector, duplicate-credit guard and TAT service all run for real against them. Times are relative, never dates. computedAmountPaise is the one invented figure (D-B unanswered), labelled as such, so the CAP is demonstrable without the RATE being right.
A98: 97 | B98: Build | C98: Phase 13 — Demo surface and assessment | D98: Write up the five answers, the signal-availability register, and the LLM decision record | F98: Task | G98: Done | H98: Done — docs/POC-ASSESSMENT.md. The five answers (U-1..U-5), the signal position in one number, and where the LLM decision stands. U-2 is reported as NOT ASSESSED and must never be quoted as passed: the fixtures were written by the same hand as the classifier, and fixtures written that way always classify well. U-4's answer is a third state the design did not anticipate — the concepts do not exist in the data at all, not 'build vs integrate'.
A99: 98 | B99: Build | C99: Phase 13 — Demo surface and assessment | D99: VerdictAssess against the exit criteria in §6 and state the go / no-go plainly | F99: Verdict | G99: Done | H99: Done — VERDICT: GO, with two conditions. Neither stop condition triggered: U-1 (process durability) and U-3 (money safety) both passed WITH their negative cases. Condition 1 is the SELECT grant + four schema answers — today the service resolves 7.7% of known monthly volume without a human because only one concern's facts are readable; the decision layer is correct and largely idle. Condition 2 is that classifier accuracy is unmeasured. Six follow-on actions listed, of which the highest-value one is not engineering work.
A100: 99 | B100: Build | C100: After the plan — demonstrability | D100: Partner console: a renderer that proves the thin-client claim | E100: Built because the person who wrote the system could not narrate it. Contains no concern name, no tier and no rule — DemoConsoleTest extracts all 38 concern codes from the migrations and fails if one appears. | F100: Task | G100: Done | H100: Done — /console under its own profile. Split from the demo profile because that one refuses to start beside a real UAT datasource, which meant the console could never show real data. Banner is read from /console/state, not written into the page. SEEN WORKING: the cap case highlights row 2, the already-paid case highlights row 1 — same table, one fact different. 218/218 green. Caught an off-by-one between Flowable's 1-based rule numbering and the file reader's 0-based index that would have highlighted the WRONG ROW on stage.
...

Sheet Evidence
A1: Spike | B1: What was tested | C1: Result | D1: What it settled
A2: 1 | B2: Flowable pause / JVM death / resume | C2: PASSED | D2: ADR-001 holds — the reason for embedding an engine at all
A3: 2 | B3: DMN hit policy and row order | C3: PASSED | D3: Row order IS logic. A table with no catch-all returns null — 13 of 38 concerns are written that way
A4: 3 | B4: REQUIRES_NEW through a rollback | C4: PASSED | D4: ADR-005 holds. Negative test passed too, so the test has teeth
A5: 4 | B5: Togglz runtime flip | C5: PASSED | D5: Kill switch works with no restart
A6: 4 | B6: Togglz misspelt flag name | C6: PASSED — A HOLE | D6: Unknown flag reads as "off" SILENTLY. Startup validation is now mandatory — FeatureNameValidator exists because of this
A7: 4 | B7: Resilience4j circuit breaker | C7: PASSED | D7: Once OPEN the body stops executing, so a dead dependency stops costing a timeout per request
A8: 4 | B8: Flyway + Flowable, one database | C8: PASSED | D8: They coexist
A9: 5 | B9: Classifier rejects bad model output | C9: PASSED | D9: Hallucinated category, confidence 1.7, prose, missing field — all stopped at the boundary
A10: — | B10: U-2 classifier accuracy | C10: NOT ASSESSED | D10: No key, no real ticket text. Must never be reported as passed
A11: build | B11: DMN modeller re-save (DMN 1.5 namespace) | C11: FOUND IN THE BUILD — A HOLE | D11: Flowable 7.0.1 parses ONLY DMN 1.3 (20191111). One re-saved file stopped dmnEngineConfiguration, killed the Spring context and failed every @SpringBootTest — 80 errors. DmnNamespaceTest guards it now
A12: build | B12: Fact name spelled differently on the two sides | C12: FOUND IN THE BUILD — A HOLE | D12: arrivedAt300m vs arrivedAt300metre. No error anywhere: the table reads null, never matches, every claim reaches an agent. ProviderContractTest guards it now
... A15: build | B15: An ACTIVE concern pointing at a BPMN file that was never written | C15: FOUND IN THE BUILD — A HOLE | D15: Non-null pointer, no artifact. Nothing failed; the partner met CONCERN_NOT_AVAILABLE and nothing reported it. SchemaAndCatalogueTest now asks both engines whether every process_key and dmn_key resolves
